rocket/__init__.py
rocket/rocket.py
rocket_amjebenamjed-1.0.0.dist-info/METADATA
rocket_amjebenamjed-1.0.0.dist-info/WHEEL
rocket_amjebenamjed-1.0.0.dist-info/top_level.txt
rocket_amjebenamjed-1.0.0.dist-info/RECORD
