Metadata-Version: 2.4
Name: rocket_amjebenamjed
Version: 1.0.0
Summary: A Python package modeling Rockets, Shuttles, and Circular Rockets with distance, area, and circumference calculations.
Home-page: https://github.com/yourusername/rocket
Author: Ben Amjed
Author-email: your_email@example.com
Classifier: Programming Language :: Python :: 3
Classifier: License :: OSI Approved :: MIT License
Classifier: Operating System :: OS Independent
Requires-Python: >=3.7
Dynamic: author
Dynamic: author-email
Dynamic: classifier
Dynamic: description
Dynamic: description-content-type
Dynamic: home-page
Dynamic: requires-python
Dynamic: summary
